Metadata-Version: 2.1
Name: parentheses
Version: 1.0.1
Summary: Light parentheses parser in Python.
Home-page: https://github.com/xzripper/parentheses
Download-URL: https://github.com/xzripper/parentheses/archive/refs/tags/v1.0.0-r.tar.gz
Author: Ivan Perzhinsky.
Author-email: name1not1found.com@gmail.com
License: MIT
Keywords: utility,string,parentheses,parsing
Classifier: Development Status :: 5 - Production/Stable 
Classifier: Intended Audience :: Developers
Classifier: Topic :: Utilities
Classifier: License :: OSI Approved :: MIT License
Classifier: Programming Language :: Python :: 3
License-File: LICENSE.txt
